zvuk_music/__init__.py
zvuk_music/base.py
zvuk_music/client.py
zvuk_music/client_async.py
zvuk_music/enums.py
zvuk_music/exceptions.py
zvuk_music/py.typed
zvuk_music/graphql/__init__.py
zvuk_music/graphql/mutations/__init__.py
zvuk_music/graphql/mutations/addItemToCollection.graphql
zvuk_music/graphql/mutations/addItemToHidden.graphql
zvuk_music/graphql/mutations/addTracksToPlaylist.graphql
zvuk_music/graphql/mutations/createPlaylist.graphql
zvuk_music/graphql/mutations/deletePlaylist.graphql
zvuk_music/graphql/mutations/removeItemFromCollection.graphql
zvuk_music/graphql/mutations/removeItemFromHidden.graphql
zvuk_music/graphql/mutations/renamePlaylist.graphql
zvuk_music/graphql/mutations/setPlaylistToPublic.graphql
zvuk_music/graphql/mutations/synthesisPlaylistBuild.graphql
zvuk_music/graphql/mutations/updataPlaylist.graphql
zvuk_music/graphql/queries/__init__.py
zvuk_music/graphql/queries/episodes.graphql
zvuk_music/graphql/queries/followingCount.graphql
zvuk_music/graphql/queries/getAllHiddenCollection.graphql
zvuk_music/graphql/queries/getArtists.graphql
zvuk_music/graphql/queries/getEpisodes.graphql
zvuk_music/graphql/queries/getFullTrack.graphql
zvuk_music/graphql/queries/getHiddenTracks.graphql
zvuk_music/graphql/queries/getPlaylistTracks.graphql
zvuk_music/graphql/queries/getPlaylists.graphql
zvuk_music/graphql/queries/getPodcasts.graphql
zvuk_music/graphql/queries/getReleases.graphql
zvuk_music/graphql/queries/getShortPlaylist.graphql
zvuk_music/graphql/queries/getStream.graphql
zvuk_music/graphql/queries/getTracks.graphql
zvuk_music/graphql/queries/listenedEpisodes.graphql
zvuk_music/graphql/queries/listeningHistory.graphql
zvuk_music/graphql/queries/notificationsHasUnread.graphql
zvuk_music/graphql/queries/profileFollowersCount.graphql
zvuk_music/graphql/queries/quickSearch.graphql
zvuk_music/graphql/queries/search.graphql
zvuk_music/graphql/queries/synthesisPlaylist.graphql
zvuk_music/graphql/queries/userCollection.graphql
zvuk_music-0.5.3.dist-info/METADATA
zvuk_music-0.5.3.dist-info/WHEEL
zvuk_music-0.5.3.dist-info/licenses/LICENSE
zvuk_music-0.5.3.dist-info/RECORD
