Metadata-Version: 2.4
Name: zvuk-music
Version: 0.5.3
Summary: Unofficial Python library for the Zvuk.com music streaming API
Project-URL: Homepage, https://github.com/trudenboy/zvuk-music
Project-URL: Documentation, https://github.com/trudenboy/zvuk-music#readme
Project-URL: Repository, https://github.com/trudenboy/zvuk-music
Project-URL: Issues, https://github.com/trudenboy/zvuk-music/issues
Project-URL: Changelog, https://github.com/trudenboy/zvuk-music/blob/main/CHANGELOG.md
Author: trudenboy
License-Expression: MIT
License-File: LICENSE
Keywords: api,music,sberzvuk,streaming,zvuk,сберзвук
Classifier: Development Status :: 4 - Beta
Classifier: Intended Audience :: Developers
Classifier: License :: OSI Approved :: MIT License
Classifier: Operating System :: OS Independent
Classifier: Programming Language :: Python :: 3
Classifier: Programming Language :: Python :: 3.9
Classifier: Programming Language :: Python :: 3.10
Classifier: Programming Language :: Python :: 3.11
Classifier: Programming Language :: Python :: 3.12
Classifier: Programming Language :: Python :: 3.13
Classifier: Topic :: Multimedia :: Sound/Audio
Classifier: Topic :: Software Development :: Libraries :: Python Modules
Classifier: Typing :: Typed
Requires-Python: >=3.9
Requires-Dist: requests>=2.28.0
Requires-Dist: typing-extensions>=4.1.0
Provides-Extra: all
Requires-Dist: aiofiles>=23.0.0; extra == 'all'
Requires-Dist: aiohttp>=3.8.0; extra == 'all'
Requires-Dist: ujson>=5.0.0; extra == 'all'
Provides-Extra: async
Requires-Dist: aiofiles>=23.0.0; extra == 'async'
Requires-Dist: aiohttp>=3.8.0; extra == 'async'
Provides-Extra: dev
Requires-Dist: mypy>=1.0.0; extra == 'dev'
Requires-Dist: pytest-asyncio>=0.21.0; extra == 'dev'
Requires-Dist: pytest-cov>=4.0.0; extra == 'dev'
Requires-Dist: pytest>=7.0.0; extra == 'dev'
Requires-Dist: ruff>=0.1.0; extra == 'dev'
Requires-Dist: types-requests>=2.28.0; extra == 'dev'
Provides-Extra: fast
Requires-Dist: ujson>=5.0.0; extra == 'fast'
